bangerbot/__init__.py
bangerbot/main.py
bangerbot/utils.py
bangerbot-0.1.4.dist-info/LICENSE.md
bangerbot-0.1.4.dist-info/METADATA
bangerbot-0.1.4.dist-info/WHEEL
bangerbot-0.1.4.dist-info/entry_points.txt
bangerbot-0.1.4.dist-info/RECORD
